llama_index/readers/google/__init__.py
llama_index/readers/google/calendar/README.md
llama_index/readers/google/calendar/__init__.py
llama_index/readers/google/calendar/base.py
llama_index/readers/google/chat/README.md
llama_index/readers/google/chat/__init__.py
llama_index/readers/google/chat/base.py
llama_index/readers/google/docs/README.md
llama_index/readers/google/docs/__init__.py
llama_index/readers/google/docs/base.py
llama_index/readers/google/drive/README.md
llama_index/readers/google/drive/__init__.py
llama_index/readers/google/drive/base.py
llama_index/readers/google/gmail/README.md
llama_index/readers/google/gmail/__init__.py
llama_index/readers/google/gmail/base.py
llama_index/readers/google/keep/README.md
llama_index/readers/google/keep/__init__.py
llama_index/readers/google/keep/base.py
llama_index/readers/google/maps/README.md
llama_index/readers/google/maps/__init__.py
llama_index/readers/google/maps/base.py
llama_index/readers/google/sheets/README.md
llama_index/readers/google/sheets/__init__.py
llama_index/readers/google/sheets/base.py
llama_index_readers_google-0.7.1.dist-info/METADATA
llama_index_readers_google-0.7.1.dist-info/WHEEL
llama_index_readers_google-0.7.1.dist-info/licenses/LICENSE
llama_index_readers_google-0.7.1.dist-info/RECORD
