Metadata-Version: 2.4
Name: llama-index-readers-google
Version: 0.7.1
Summary: llama-index readers google integration
Author-email: Your Name <you@example.com>
Maintainer: bbornsztein, jerryjliu, metanov, ong, piroz, pycui, ravi03071991
License-Expression: MIT
License-File: LICENSE
Keywords: email,gmail,google keep,google maps,google notes
Requires-Python: <4.0,>=3.10
Requires-Dist: gkeepapi<0.16,>=0.15.1
Requires-Dist: google-api-python-client<3,>=2.115.0
Requires-Dist: google-auth-httplib2<0.3,>=0.2.0
Requires-Dist: google-auth-oauthlib<2,>=1.2.0
Requires-Dist: llama-index-core<0.14,>=0.13.0
Requires-Dist: pandas
Requires-Dist: pydrive<2,>=1.3.1
